adafruit_ntp.py
adafruit_circuitpython_ntp-3.3.5.dist-info/licenses/LICENSE
adafruit_circuitpython_ntp-3.3.5.dist-info/METADATA
adafruit_circuitpython_ntp-3.3.5.dist-info/WHEEL
adafruit_circuitpython_ntp-3.3.5.dist-info/top_level.txt
adafruit_circuitpython_ntp-3.3.5.dist-info/RECORD
