Metadata-Version: 2.4
Name: adafruit-circuitpython-ntp
Version: 3.3.5
Summary: Network Time Protocol (NTP) helper for Python
Author-email: Adafruit Industries <circuitpython@adafruit.com>
License: MIT
Project-URL: Homepage, https://github.com/adafruit/Adafruit_CircuitPython_NTP
Keywords: adafruit,blinka,circuitpython,micropython,ntp,ntp,,network,,time
Classifier: Intended Audience :: Developers
Classifier: Topic :: Software Development :: Libraries
Classifier: Topic :: Software Development :: Embedded Systems
Classifier: Topic :: System :: Hardware
Classifier: License :: OSI Approved :: MIT License
Classifier: Programming Language :: Python :: 3
License-File: LICENSE
Requires-Dist: Adafruit-Blinka
Provides-Extra: optional
Dynamic: license-file
